{
  "patrolId": "patrol4",
  "spawnLocationDetails": {
    "latitude": 52.913920792614,
    "longitude": -0.374034478632225,
    "addressLine": "Holland Road",
    "locality": "Sleaford",
    "neighborhood": "",
    "adminDivision": "England",
    "adminDivision2": "Lincs",
    "countryIso2": "GB",
    "countryRegion": "United Kingdom",
    "postalCode": "NG34 0BQ",
    "formattedAddress": "Holland Road, NG34 0BQ, England, United Kingdom"
  },
  "currentLoc": [
    52.913920792614,
    -0.374034478632225
  ]
}